<?xml version="1.0" ?>
<rooms>
	<room variant="0" name="Sunil_B - Technophobes" type="1" subtype="0" shape="12" width="26" height="14" difficulty="1" weight="1.0" lastTestTime="2021-12-09T22:55+00:00">
		<door exists="True" x="-1" y="3"/>
		<door exists="True" x="-1" y="10"/>
		<door exists="True" x="6" y="-1"/>
		<door exists="True" x="6" y="14"/>
		<door exists="True" x="13" y="10"/>
		<door exists="True" x="19" y="-1"/>
		<door exists="True" x="19" y="7"/>
		<door exists="True" x="26" y="3"/>
		<spawn x="0" y="0">
			<entity type="1000" variant="0" subtype="1" weight="1.0"/>
		</spawn>
		<spawn x="1" y="0">
			<entity type="1000" variant="0" subtype="0" weight="1.0"/>
		</spawn>
		<spawn x="2" y="0">
			<entity type="1000" variant="0" subtype="0" weight="1.0"/>
		</spawn>
		<spawn x="3" y="0">
			<entity type="1000" variant="0" subtype="0" weight="1.0"/>
		</spawn>
		<spawn x="4" y="0">
			<entity type="1000" variant="0" subtype="1" weight="1.0"/>
		</spawn>
		<spawn x="11" y="0">
			<entity type="1000" variant="0" subtype="0" weight="1.0"/>
		</spawn>
		<spawn x="12" y="0">
			<entity type="1000" variant="0" subtype="0" weight="1.0"/>
		</spawn>
		<spawn x="13" y="0">
			<entity type="1000" variant="0" subtype="0" weight="1.0"/>
		</spawn>
		<spawn x="14" y="0">
			<entity type="1000" variant="0" subtype="0" weight="1.0"/>
		</spawn>
		<spawn x="15" y="0">
			<entity type="1000" variant="0" subtype="0" weight="1.0"/>
		</spawn>
		<spawn x="23" y="0">
			<entity type="1000" variant="0" subtype="0" weight="1.0"/>
		</spawn>
		<spawn x="24" y="0">
			<entity type="1000" variant="0" subtype="0" weight="1.0"/>
		</spawn>
		<spawn x="25" y="0">
			<entity type="1000" variant="0" subtype="0" weight="1.0"/>
		</spawn>
		<spawn x="0" y="1">
			<entity type="1000" variant="0" subtype="1" weight="1.0"/>
		</spawn>
		<spawn x="1" y="1">
			<entity type="1000" variant="0" subtype="1" weight="1.0"/>
		</spawn>
		<spawn x="13" y="1">
			<entity type="1000" variant="0" subtype="0" weight="1.0"/>
		</spawn>
		<spawn x="14" y="1">
			<entity type="1000" variant="0" subtype="0" weight="1.0"/>
		</spawn>
		<spawn x="24" y="1">
			<entity type="1000" variant="0" subtype="1" weight="1.0"/>
		</spawn>
		<spawn x="25" y="1">
			<entity type="1000" variant="0" subtype="0" weight="1.0"/>
		</spawn>
		<spawn x="0" y="2">
			<entity type="1000" variant="0" subtype="0" weight="1.0"/>
		</spawn>
		<spawn x="3" y="2">
			<entity type="6" variant="1020" subtype="0" weight="1.0"/>
		</spawn>
		<spawn x="17" y="2">
			<entity type="6" variant="1022" subtype="0" weight="1.0"/>
		</spawn>
		<spawn x="21" y="2">
			<entity type="6" variant="1021" subtype="0" weight="1.0"/>
		</spawn>
		<spawn x="3" y="3">
			<entity type="999" variant="1990" subtype="2176" weight="1.0"/>
		</spawn>
		<spawn x="7" y="3">
			<entity type="1000" variant="0" subtype="0" weight="1.0"/>
		</spawn>
		<spawn x="8" y="3">
			<entity type="1000" variant="0" subtype="0" weight="1.0"/>
		</spawn>
		<spawn x="14" y="3">
			<entity type="1000" variant="0" subtype="0" weight="1.0"/>
		</spawn>
		<spawn x="15" y="3">
			<entity type="1000" variant="0" subtype="0" weight="1.0"/>
		</spawn>
		<spawn x="17" y="3">
			<entity type="999" variant="1990" subtype="2178" weight="1.0"/>
		</spawn>
		<spawn x="21" y="3">
			<entity type="999" variant="1990" subtype="2177" weight="1.0"/>
		</spawn>
		<spawn x="6" y="4">
			<entity type="1000" variant="0" subtype="0" weight="1.0"/>
		</spawn>
		<spawn x="7" y="4">
			<entity type="1000" variant="0" subtype="0" weight="1.0"/>
		</spawn>
		<spawn x="8" y="4">
			<entity type="1000" variant="0" subtype="0" weight="1.0"/>
		</spawn>
		<spawn x="9" y="4">
			<entity type="1000" variant="0" subtype="0" weight="1.0"/>
		</spawn>
		<spawn x="13" y="4">
			<entity type="1000" variant="0" subtype="0" weight="1.0"/>
		</spawn>
		<spawn x="14" y="4">
			<entity type="1000" variant="0" subtype="0" weight="1.0"/>
		</spawn>
		<spawn x="7" y="5">
			<entity type="1000" variant="0" subtype="0" weight="1.0"/>
		</spawn>
		<spawn x="8" y="5">
			<entity type="1000" variant="0" subtype="0" weight="1.0"/>
		</spawn>
		<spawn x="23" y="5">
			<entity type="1000" variant="0" subtype="0" weight="1.0"/>
		</spawn>
		<spawn x="24" y="5">
			<entity type="1000" variant="0" subtype="1" weight="1.0"/>
		</spawn>
		<spawn x="3" y="6">
			<entity type="1000" variant="0" subtype="0" weight="1.0"/>
		</spawn>
		<spawn x="22" y="6">
			<entity type="1000" variant="0" subtype="0" weight="1.0"/>
		</spawn>
		<spawn x="23" y="6">
			<entity type="1000" variant="0" subtype="0" weight="1.0"/>
		</spawn>
		<spawn x="24" y="6">
			<entity type="1000" variant="0" subtype="0" weight="1.0"/>
		</spawn>
		<spawn x="25" y="6">
			<entity type="1000" variant="0" subtype="0" weight="1.0"/>
		</spawn>
		<spawn x="2" y="7">
			<entity type="1000" variant="0" subtype="0" weight="1.0"/>
		</spawn>
		<spawn x="3" y="7">
			<entity type="1000" variant="0" subtype="0" weight="1.0"/>
		</spawn>
		<spawn x="4" y="7">
			<entity type="1000" variant="0" subtype="0" weight="1.0"/>
		</spawn>
		<spawn x="2" y="8">
			<entity type="1000" variant="0" subtype="0" weight="1.0"/>
		</spawn>
		<spawn x="3" y="8">
			<entity type="1000" variant="0" subtype="0" weight="1.0"/>
		</spawn>
		<spawn x="4" y="8">
			<entity type="1000" variant="0" subtype="0" weight="1.0"/>
		</spawn>
		<spawn x="3" y="9">
			<entity type="1000" variant="0" subtype="0" weight="1.0"/>
		</spawn>
		<spawn x="8" y="10">
			<entity type="1000" variant="0" subtype="0" weight="1.0"/>
		</spawn>
		<spawn x="9" y="10">
			<entity type="1000" variant="0" subtype="0" weight="1.0"/>
		</spawn>
		<spawn x="0" y="11">
			<entity type="1000" variant="0" subtype="1" weight="1.0"/>
		</spawn>
		<spawn x="8" y="11">
			<entity type="1000" variant="0" subtype="0" weight="1.0"/>
		</spawn>
		<spawn x="9" y="11">
			<entity type="1000" variant="0" subtype="0" weight="1.0"/>
		</spawn>
		<spawn x="0" y="12">
			<entity type="1000" variant="0" subtype="1" weight="1.0"/>
		</spawn>
		<spawn x="1" y="12">
			<entity type="1000" variant="0" subtype="1" weight="1.0"/>
		</spawn>
		<spawn x="12" y="12">
			<entity type="1000" variant="0" subtype="0" weight="1.0"/>
		</spawn>
		<spawn x="0" y="13">
			<entity type="1000" variant="0" subtype="0" weight="1.0"/>
		</spawn>
		<spawn x="1" y="13">
			<entity type="1000" variant="0" subtype="0" weight="1.0"/>
		</spawn>
		<spawn x="2" y="13">
			<entity type="1000" variant="0" subtype="0" weight="1.0"/>
		</spawn>
		<spawn x="3" y="13">
			<entity type="1000" variant="0" subtype="0" weight="1.0"/>
		</spawn>
		<spawn x="11" y="13">
			<entity type="1000" variant="0" subtype="0" weight="1.0"/>
		</spawn>
		<spawn x="12" y="13">
			<entity type="1000" variant="0" subtype="0" weight="1.0"/>
		</spawn>
	</room>
</rooms>
